socketdev/__init__.py
socketdev/exceptions.py
socketdev/log.py
socketdev/version.py
socketdev/alertfullscansearch/__init__.py
socketdev/alerts/__init__.py
socketdev/alerttypes/__init__.py
socketdev/analytics/__init__.py
socketdev/apitokens/__init__.py
socketdev/auditlog/__init__.py
socketdev/basics/__init__.py
socketdev/core/api.py
socketdev/core/classes.py
socketdev/core/dedupe.py
socketdev/core/issues.py
socketdev/dependencies/__init__.py
socketdev/diffscans/__init__.py
socketdev/export/__init__.py
socketdev/fixes/__init__.py
socketdev/fullscans/__init__.py
socketdev/historical/__init__.py
socketdev/labels/__init__.py
socketdev/licensemetadata/__init__.py
socketdev/npm/__init__.py
socketdev/openapi/__init__.py
socketdev/org/__init__.py
socketdev/purl/__init__.py
socketdev/quota/__init__.py
socketdev/report/__init__.py
socketdev/repos/__init__.py
socketdev/repositories/__init__.py
socketdev/sbom/__init__.py
socketdev/settings/__init__.py
socketdev/supportedfiles/__init__.py
socketdev/telemetry/__init__.py
socketdev/threatfeed/__init__.py
socketdev/tools/__init__.py
socketdev/triage/__init__.py
socketdev/uploadmanifests/__init__.py
socketdev/utils/__init__.py
socketdev/webhooks/__init__.py
socketdev-3.0.29.dist-info/METADATA
socketdev-3.0.29.dist-info/WHEEL
socketdev-3.0.29.dist-info/licenses/LICENSE
socketdev-3.0.29.dist-info/RECORD
