Metadata-Version: 2.4
Name: socketdev
Version: 3.0.29
Summary: Socket Security Python SDK
Project-URL: Homepage, https://github.com/socketdev/socketdev
Author-email: Douglas Coburn <douglas@socket.dev>
Maintainer-email: Douglas Coburn <douglas@socket.dev>
License: MIT License
License-File: LICENSE
Keywords: oss,sca,sdk,security,socket.dev,socketsecurity
Classifier: Development Status :: 5 - Production/Stable
Classifier: Intended Audience :: Developers
Classifier: Programming Language :: Python :: 3.9
Classifier: Programming Language :: Python :: 3.10
Classifier: Programming Language :: Python :: 3.11
Classifier: Programming Language :: Python :: 3.12
Classifier: Programming Language :: Python :: 3.13
Classifier: Programming Language :: Python :: 3.14
Requires-Python: >=3.9
Requires-Dist: requests
Requires-Dist: typing-extensions>=4.12.2
Provides-Extra: dev
Requires-Dist: hatch>=1.14.0; extra == 'dev'
Requires-Dist: hatchling>=1.27.0; extra == 'dev'
Requires-Dist: ruff>=0.3.0; extra == 'dev'
Requires-Dist: twine>=4.0.0; extra == 'dev'
Provides-Extra: test
Requires-Dist: pytest-cov>=4.0.0; extra == 'test'
Requires-Dist: pytest>=7.0.0; extra == 'test'
